server.py
fusebase_mcp-1.0.2.dist-info/METADATA
fusebase_mcp-1.0.2.dist-info/WHEEL
fusebase_mcp-1.0.2.dist-info/entry_points.txt
fusebase_mcp-1.0.2.dist-info/top_level.txt
fusebase_mcp-1.0.2.dist-info/RECORD
