Metadata-Version: 2.4
Name: fusebase-mcp
Version: 1.0.2
Summary: Add your description here
Requires-Python: >=3.11
Requires-Dist: httpx>=0.28.1
Requires-Dist: mcp[cli]>=1.6.0
